pietoolbelt/__init__.py
pietoolbelt/img_matcher.py
pietoolbelt/mask_composer.py
pietoolbelt/tiles_utils.py
pietoolbelt/train_config.py
pietoolbelt/tta.py
pietoolbelt/utils.py
pietoolbelt/viz.py
pietoolbelt/augmentations/__init__.py
pietoolbelt/augmentations/common.py
pietoolbelt/augmentations/detection.py
pietoolbelt/augmentations/segmentation.py
pietoolbelt/datasets/__init__.py
pietoolbelt/datasets/common.py
pietoolbelt/datasets/utils.py
pietoolbelt/losses/__init__.py
pietoolbelt/losses/common.py
pietoolbelt/losses/regression.py
pietoolbelt/losses/segmentation.py
pietoolbelt/metrics/__init__.py
pietoolbelt/metrics/common.py
pietoolbelt/metrics/cpu/__init__.py
pietoolbelt/metrics/cpu/classification.py
pietoolbelt/metrics/cpu/detection.py
pietoolbelt/metrics/cpu/regression.py
pietoolbelt/metrics/cpu/segmentation.py
pietoolbelt/metrics/torch/__init__.py
pietoolbelt/metrics/torch/classification.py
pietoolbelt/metrics/torch/detection.py
pietoolbelt/metrics/torch/regression.py
pietoolbelt/metrics/torch/segmentation.py
pietoolbelt/models/__init__.py
pietoolbelt/models/albunet.py
pietoolbelt/models/utils.py
pietoolbelt/models/weights_storage.py
pietoolbelt/models/decoders/__init__.py
pietoolbelt/models/decoders/ssd.py
pietoolbelt/models/decoders/unet.py
pietoolbelt/models/encoders/__init__.py
pietoolbelt/models/encoders/common.py
pietoolbelt/models/encoders/inception.py
pietoolbelt/models/encoders/mobile_net.py
pietoolbelt/models/encoders/resnet.py
pietoolbelt/monitors/__init__.py
pietoolbelt/monitors/mlflow_monithor.py
pietoolbelt/pipeline/__init__.py
pietoolbelt/pipeline/abstract_step.py
pietoolbelt/pipeline/stratification.py
pietoolbelt/pipeline/thrsholds_search.py
pietoolbelt/pipeline/train.py
pietoolbelt/pipeline/bagging/__init__.py
pietoolbelt/pipeline/bagging/common.py
pietoolbelt/pipeline/inference/__init__.py
pietoolbelt/pipeline/inference/segmentation.py
pietoolbelt/pipeline/metrics_calc/__init__.py
pietoolbelt/pipeline/metrics_calc/common.py
pietoolbelt-0.3.26.dist-info/LICENSE
pietoolbelt-0.3.26.dist-info/METADATA
pietoolbelt-0.3.26.dist-info/WHEEL
pietoolbelt-0.3.26.dist-info/top_level.txt
pietoolbelt-0.3.26.dist-info/RECORD
