Metadata-Version: 2.1
Name: pietoolbelt
Version: 0.3.26
Summary: Toolbelt for PiePline training pipeline
Home-page: https://github.com/PiePline/PieToolbelt
Author: Anton Fedotov
Author-email: anton.fedotov.af@gmail.com
License: UNKNOWN
Platform: UNKNOWN
Classifier: Development Status :: 3 - Alpha
Classifier: Programming Language :: Python :: 3
Classifier: License :: OSI Approved :: MIT License
Classifier: Intended Audience :: Developers
Classifier: Intended Audience :: Science/Research
Classifier: Operating System :: OS Independent
Classifier: Programming Language :: Python :: 3.5
Classifier: Programming Language :: Python :: 3.6
Classifier: Programming Language :: Python :: 3.7
Classifier: Programming Language :: Python :: 3.8
Classifier: Topic :: Scientific/Engineering
Classifier: Topic :: Scientific/Engineering :: Artificial Intelligence
Classifier: Topic :: Scientific/Engineering :: Image Recognition
Classifier: Topic :: Software Development :: Libraries
Classifier: Topic :: Software Development :: Libraries :: Python Modules
Requires-Dist: piepline (~=0.3.0)
Requires-Dist: opencv-python
Requires-Dist: scikit-learn
Requires-Dist: numpy
Requires-Dist: tqdm
Requires-Dist: torch (>=0.4.1)
Requires-Dist: torchvision
Requires-Dist: sklearn
Requires-Dist: albumentations
Requires-Dist: mlflow (==1.15.0)
Requires-Dist: boto3
